3a49525171c7d4218706__mypyc.cpython-310-darwin.so
quatint-0.0.7.dist-info/RECORD
quatint-0.0.7.dist-info/WHEEL
quatint-0.0.7.dist-info/top_level.txt
quatint-0.0.7.dist-info/METADATA
quatint-0.0.7.dist-info/licenses/LICENSE
quatint/quat.cpython-310-darwin.so
quatint/__init__.cpython-310-darwin.so
quatint-stubs/quat.pyi
quatint-stubs/__init__.pyi
