Metadata-Version: 2.4
Name: quatint
Version: 0.0.7
Summary: A quatint class, for using quaternions backed by integers and half-integers (Hurwitz integers).
Author-email: Ryan Heard <ryanwheard@gmail.com>
License: MIT
Project-URL: Repository, https://github.com/rheard/quatint
Keywords: complex,math
Classifier: Programming Language :: Python :: 3
Classifier: Programming Language :: Python :: 3.9
Classifier: Programming Language :: Python :: 3.10
Classifier: Programming Language :: Python :: 3.11
Classifier: Programming Language :: Python :: 3.12
Classifier: Programming Language :: Python :: 3.13
Classifier: Programming Language :: Python :: 3.14
Classifier: Programming Language :: Python :: Implementation :: CPython
Requires-Python: >=3.9
License-File: LICENSE
Requires-Dist: sympy<=1.12.1
Dynamic: license
Dynamic: license-file
